bobtemplates.odoo-3.4-py3.12-nspkg.pth
bobtemplates/odoo/__init__.py
bobtemplates/odoo/hooks.py
bobtemplates/odoo/addon/.mrbob.ini
bobtemplates/odoo/addon/+addon.name+/README.rst.bob
bobtemplates/odoo/addon/+addon.name+/__init__.py
bobtemplates/odoo/addon/+addon.name+/__openerp__.py.bob
bobtemplates/odoo/addon/+addon.name+/readme/dummy.txt
bobtemplates/odoo/addon/+addon.name+/static/description/icon.png.oca
bobtemplates/odoo/model/.mrbob.ini
bobtemplates/odoo/model/demo/+model.name_underscored+.xml.bob
bobtemplates/odoo/model/models/+model.name_underscored+.py.bob
bobtemplates/odoo/model/security/+model.name_underscored+.xml.bob
bobtemplates/odoo/model/views/+model.name_underscored+.xml.bob
bobtemplates/odoo/readme/.mrbob.ini
bobtemplates/odoo/readme/README.rst.bob
bobtemplates/odoo/readme/readme/dummy.txt
bobtemplates/odoo/test/.mrbob.ini
bobtemplates/odoo/test/tests/+test.name_underscored+.py.bob
bobtemplates/odoo/wizard/.mrbob.ini
bobtemplates/odoo/wizard/wizards/+wizard.name_underscored+.py.bob
bobtemplates/odoo/wizard/wizards/+wizard.name_underscored+.xml.bob
bobtemplates_odoo-3.4.dist-info/licenses/LICENSE
bobtemplates_odoo-3.4.dist-info/METADATA
bobtemplates_odoo-3.4.dist-info/WHEEL
bobtemplates_odoo-3.4.dist-info/namespace_packages.txt
bobtemplates_odoo-3.4.dist-info/top_level.txt
bobtemplates_odoo-3.4.dist-info/RECORD
