Metadata-Version: 2.4
Name: bobtemplates.odoo
Version: 3.4
Summary: mr.bob templates for Odoo projects
Home-page: http://github.com/acsone/bobtemplates.odoo
Author: ACSONE SA/NV
Author-email: info@acsone.eu
License: LGPLv3
Classifier: Development Status :: 5 - Production/Stable
Classifier: Intended Audience :: Developers
Classifier: License :: OSI Approved :: GNU Affero General Public License v3 or later (AGPLv3+)
Classifier: Operating System :: OS Independent
Classifier: Programming Language :: Python
Classifier: Framework :: Odoo
Requires-Python: >=3.7
License-File: LICENSE
Requires-Dist: mr.bob
Requires-Dist: requests
Dynamic: author
Dynamic: author-email
Dynamic: classifier
Dynamic: description
Dynamic: home-page
Dynamic: license
Dynamic: license-file
Dynamic: requires-dist
Dynamic: requires-python
Dynamic: summary
